Metadata-Version: 2.1
Name: planetscope
Version: 0.1
Summary: The planetscope package is a tool specifically designed to read and plot data from the PlanetScope satellite imaging system.
Home-page: https://github.com/ankurk017/planet_utilities
Author: Ankur Kumar
Author-email: ankurk017@gmail.com
License: MIT
Platform: UNKNOWN
License-File: LICENSE
